remote_control/__init__.py
remote_control/cliente.py
remote_control/server.py
pyroar_remote_control-0.1.3.dist-info/entry_points.txt
pyroar_remote_control-0.1.3.dist-info/METADATA
pyroar_remote_control-0.1.3.dist-info/WHEEL
pyroar_remote_control-0.1.3.dist-info/RECORD
